{
  "resumes": [
    {
      "filename": "resume (3) (1).pdf",
      "upload_timestamp": "2025-08-15T19:21:09.045825",
      "extracted_text": "Ashutosh\n \nDas\n \nShakti\n \nNagar\n \nPada,\n \nBhawanipatna,\n \nKalahandi\n \nashutoshd072@gmail.com\n \n+91-6371303228\n \nGitHub:\n \nAshutoshdas-dev\n \nLinkedI\nn:\n \nlinkedin.com/in/ashutosh-das-59a\n4\n \n \n \nProfessional\n \nSummary\n \nI\n \nam\n \na\n \nhighly\n \nmotivated\n \nand\n \ndetail-oriented\n \nsecond-year\n \nComputer\n \nScience\n \nstudent\n \nspecializing\n \nin\n \nAI\n \nand\n \nMachine\n \nLearning.\n \nI\n \nhave\n \na\n \nproven\n \nability\n \nto\n \ndevelop\n \nscalable\n \nAI\n \nmodels,\n \noptimize\n \ndeep\n \nlearning\n \npipelines,\n \nand\n \ndeploy\n \nML\n \nsolutions\n \non\n \ncloud\n \nplatforms.\n \nPassionate\n \nabout\n \nleveraging\n \ninnovative\n \nAI\n \ntechnologies\n \nto\n \nsolve\n \ncomplex\n \nproblems\n \nand\n \nmake\n \nimpactful\n \nopen-source\n \ncontributions.\n \nEducation\n \nGandhi\n \nInstitute\n \nof\n \nEngineering\n \nand\n \nTechnology\n \nUniversity,\n \nOdisha,\n \nGunupur\n \nB.Tech\n \nin\n \nAI\n \n&\n \nML\n \n(2023\n \n–\n \n2027)\n \nCGPA:\n \n7.62\n \nPragati\n \nConcept\n \nSchool\n \nHigher\n \nSecondary\n \n(2021\n \n–\n \n2023)\n \nMark:\n \n70%\n \nVimala\n \nConvent\n \nSchool\n \nICSE\n \n(Up\n \nto\n \n2021)\n \nMark:\n \n85%\n \nTechnical\n \nSkills\n \n•\n \nProgramming\n \nLanguages:\n \nPython,\n \nJavaScript,\n \nJava(with\n \nObject-Oriented\n \nProgramming\n \n(OOP))\n \n•\n \nAI\n \n&\n \nMachine\n \nLearning:\n \nTensorFlow(basic),\n \nLarge\n \nLanguage\n \nModels\n \n(LLMs),\n \nChatGPT\n \nAPI,\n \nConvolutional\n \nNeural\n \nNetworks\n \n(CNNs)(basic),\n \nGoogle\n \nColab,\n \nTensorFlow\n \nLite(basic),\n \nModel\n \nDeployment,\n \nComputer\n \nVision,Version\n \nControl\n \n(e.g.,\n \nGit)\n \n•\n \nCloud\n \n&\n \nDeployment:\n \nGoogle\n \nCloud\n \nPlatform\n \n(GCP),\n \nDocker\n \n(Basic\n \nto\n \nIntermediate),\n \nFlask,\n \nREST\n \nAPIs\n \n•\n \nWeb\n \nDevelopment:\n \nReact.js,\n \nExpress.js,\n \nflask,\n \nScalable\n \nBackend\n \nDesign\n \nProjects\n \n•\n \nReact\n \nBlogging\n \nWebsite\n \nGitHub:\n \nreact\n \nblogging\n \nwebsite\n \nDeveloped\n \na\n \nresponsive\n \nblogging\n \nplatform\n \nusing\n \nReact.js\n \nand\n \nNode.js\n \nwith\n \nAPI\n \nIntegration\n \nand\n \ndatabase\n \nintegration.\n \n•\n \nMovie\n \nRecommender\n \nSystem\n \nGitHub:\n \nMovie-Recommender-System\n \nBuilt\n \na\n \nrecommendation\n \nsystem\n \nusing\n \ncollaborative\n \nfiltering\n \nwith\n \nPython\n \nand\n \nscikit-learn,\n \nachieving\n \na\n \n20%\n \nimprovement\n \nin\n \nrecommendation\n \naccuracy.\n \n•\n \nHandwriting\n \nRecognition\n \nSystem\n \n \nDeveloped\n \na\n \nCNN-based\n \nmodel\n \nusing\n \nthe\n \nEMNIST\n \ndataset\n \nin\n \nGoogle\n \nColab,\n \noptimized\n \nfor\n \n90%+\n \naccuracy,\n \nand\n \ndeployed\n \nwith\n \nTensorFlow\n \nLite\n \nin\n \na\n \nDockerized\n \nenvironment\n \non\n \nan\n \nM2\n \nMac.\n \nImproved\n \ntraining\n \nefficiency\n \nby\n \n30%\n \nusing\n \ndata\n \naugmentation.\n \n•\n \nOnLook\n \n–\n \nOpen\n \nSource\n \nProject\n \nGitHub:\n \nOnLook\n \nContributed\n \nto\n \nan\n \nopen-source\n \nproject\n \nfocused\n \non\n \nenhancing\n \nuser\n \nexperience\n \nand\n \ninterface\n \naesthetics\n \nby\n \nimproving\n \nUI\n \nresponsiveness\n \nand\n \noverall\n \nperformance.\n \nSoft\n \nSkills\n \n•\n \nProblem-Solving:\n \nStrong\n \nanalytical\n \nand\n \ndebugging\n \nskills\n \nwith\n \na\n \nfocus\n \non\n \noptimizing\n \nAI\n \nmodels.\n \n•\n \nCommunication:\n \nEffective\n \nin\n \npresenting\n \ncomplex\n \nAI\n \nsolutions\n \nto\n \nboth\n \ntechnical\n \nand\n \nnon-technical\n \nstakeholders.\n \n•\n \nTeamwork:\n \nProven\n \nexperience\n \nin\n \nagile\n \nand\n \ncollaborative\n \nenvironments,\n \ncontributing\n \nto\n \ncross-functional\n \nteams.\n \n•\n \nAdaptability:\n \nQuick\n \nlearner\n \nadept\n \nat\n \nmastering\n \nnew\n \nAI\n \ntools\n \nand\n \nframeworks\n \nin\n \ndynamic\n \nsettings.\n \n\n",
      "parsed_resume": {
        "contact_info": {
          "email": "ashutoshd072@gmail.com",
          "phone": "+91-6371303228",
          "linkedin": "linkedin.com/in/ashutosh-das-59a"
        },
        "education": [
          {
            "degree": "ma",
            "context": "Pada,\n \nBhawanipatna,\n \nKalahandi\n \nashutoshd072@gmail.com\n \n+91-6371303228\n \nGitHub:\n \nAshutoshdas-de"
          },
          {
            "degree": "ma",
            "context": "com/in/ashutosh-das-59a\n4\n \n \n \nProfessional\n \nSummary\n \nI\n \nam\n \na\n \nhighly\n \nmotivated\n \nand\n \ndetai"
          },
          {
            "degree": "Ma",
            "context": "cience\n \nstudent\n \nspecializing\n \nin\n \nAI\n \nand\n \nMachine\n \nLearning.\n \nI\n \nhave\n \na\n \nproven\n \nabilit"
          }
        ],
        "experience": [],
        "skills": {
          "programming_languages": [
            "javascript",
            "java",
            "python",
            "js"
          ],
          "frameworks_libraries": [
            "react",
            "flask",
            "express",
            "tensorflow",
            "scikit-learn"
          ],
          "tools_technologies": [
            "github",
            "git"
          ],
          "cloud_platforms": [
            "google cloud",
            "gcp"
          ],
          "methodologies": [
            "agile"
          ],
          "soft_skills": [
            "analytical",
            "cross-functional",
            "communication",
            "teamwork",
            "innovative",
            "training"
          ],
          "web_technologies": [
            "rest",
            "api"
          ],
          "data_science": [
            "neural networks",
            "machine learning",
            "computer vision",
            "deep learning"
          ],
          "devops": [
            "docker"
          ]
        },
        "certifications": [],
        "summary": "Ashutosh\n \nDas\n \nShakti\n \nNagar\n \nPada,\n \nBhawanipatna,\n \nKalahandi\n \nashutoshd072@gmail.com\n \n+91-6371303228\n \nGitHub:\n \nAshutoshdas-dev\n \nLinkedI\nn:\n \nlinkedin.com/in/ashutosh-das-59a\n4\n \n \n \nProfessional\n \nSummary\n \nI\n \nam\n \na\n \nhighly\n \nmotivated\n \nand\n \ndetail-oriented\n \nsecond-year\n \nComputer\n \nScience\n \nstudent\n \nspecializing\n \nin\n \nAI\n \nand\n \nMachine\n \nLearning.\n \nI\n \nhave\n \na\n \nproven\n \nability\n \nto\n \ndevelop\n \nscalable\n \nAI\n \nmodels,\n \noptimize\n \ndeep\n \nlearning\n \npipelines,\n \nand\n \nde",
        "projects": []
      },
      "extracted_skills": {
        "programming_languages": [
          "javascript",
          "java",
          "python",
          "js"
        ],
        "frameworks_libraries": [
          "react",
          "flask",
          "express",
          "tensorflow",
          "scikit-learn"
        ],
        "tools_technologies": [
          "github",
          "git"
        ],
        "cloud_platforms": [
          "google cloud",
          "gcp"
        ],
        "methodologies": [
          "agile"
        ],
        "soft_skills": [
          "analytical",
          "cross-functional",
          "communication",
          "teamwork",
          "innovative",
          "training"
        ],
        "web_technologies": [
          "rest",
          "api"
        ],
        "data_science": [
          "neural networks",
          "machine learning",
          "computer vision",
          "deep learning"
        ],
        "devops": [
          "docker"
        ]
      },
      "total_skills_found": 27
    },
    {
      "filename": "resume (3) (1).pdf",
      "timestamp": "2025-08-15T19:27:19.895141",
      "skills_found": 27,
      "ats_score": 68,
      "job_matches": 4
    },
    {
      "filename": "resume (3) (1).pdf",
      "timestamp": "2025-08-15T19:28:23.162745",
      "skills_found": 27,
      "ats_score": 65,
      "job_matches": 4
    },
    {
      "filename": "resume (3).pdf",
      "timestamp": "2025-08-16T12:40:44.404223",
      "skills_found": 27,
      "ats_score": 43,
      "job_matches": 0
    },
    {
      "filename": "resume (3).pdf",
      "timestamp": "2025-08-16T12:43:14.700771",
      "skills_found": 27,
      "ats_score": 43,
      "job_matches": 0
    },
    {
      "filename": "resume (3).pdf",
      "timestamp": "2025-08-16T12:57:01.073023",
      "skills_found": 27,
      "ats_score": 43,
      "job_matches": 4
    },
    {
      "filename": "resume (3).pdf",
      "timestamp": "2025-08-17T14:40:06.959854",
      "skills_found": 27,
      "ats_score": 43,
      "job_matches": 4
    },
    {
      "filename": "resume (3).pdf",
      "timestamp": "2025-08-17T16:22:39.108000",
      "skills_found": 27,
      "ats_score": 43,
      "job_matches": 4
    },
    {
      "filename": "resume (3).pdf",
      "timestamp": "2025-08-18T05:42:54.867091",
      "skills_found": 27,
      "ats_score": 43,
      "job_matches": 4
    },
    {
      "filename": "resume (3) (1).pdf",
      "timestamp": "2025-09-29T14:35:22.046498",
      "skills_found": 27,
      "ats_score": 43,
      "job_matches": 0
    },
    {
      "filename": "test_resume.txt",
      "timestamp": "2025-10-09T09:34:10.912991",
      "skills_found": 22,
      "ats_score": 67,
      "job_matches": 0
    },
    {
      "filename": "resume (3) (1).pdf",
      "timestamp": "2025-10-09T09:34:29.035371",
      "skills_found": 27,
      "ats_score": 68,
      "job_matches": 0
    },
    {
      "filename": "resume (3) (1).pdf",
      "timestamp": "2025-10-09T10:11:29.379294",
      "skills_found": 27,
      "ats_score": 68,
      "job_matches": 0
    },
    {
      "filename": "resume (3) (1).pdf",
      "timestamp": "2025-10-09T10:24:11.281889",
      "skills_found": 27,
      "ats_score": 68,
      "job_matches": 0
    },
    {
      "filename": "resume (3) (1).pdf",
      "timestamp": "2025-10-09T10:40:23.181145",
      "skills_found": 27,
      "ats_score": 68,
      "job_matches": 0
    },
    {
      "filename": "resume (3).pdf",
      "timestamp": "2025-10-09T10:48:42.616368",
      "skills_found": 27,
      "ats_score": 67,
      "job_matches": 0
    },
    {
      "filename": "resume (3).pdf",
      "timestamp": "2025-10-09T10:51:43.286252",
      "skills_found": 27,
      "ats_score": 67,
      "job_matches": 0
    },
    {
      "filename": "resume (3).pdf",
      "timestamp": "2025-10-09T10:53:59.293206",
      "skills_found": 27,
      "ats_score": 67,
      "job_matches": 0
    }
  ]
}